MANIFEST.in
README.md
README.rst
setup.py
scipy_psdm/__init__.py
scipy_psdm/luriegold.py
scipy_psdm/utils.py
scipy_psdm.egg-info/PKG-INFO
scipy_psdm.egg-info/SOURCES.txt
scipy_psdm.egg-info/dependency_links.txt
scipy_psdm.egg-info/requires.txt
scipy_psdm.egg-info/top_level.txt
scipy_psdm.egg-info/zip-safe
test/__init__.py
test/test_luriegold.py