Metadata-Version: 1.2
Name: scipy-psdm
Version: 0.2.2
Summary: transform an ill-conditioned quadratic matrix to a positive semidefinite matrix
Home-page: http://github.com/ulf1/scipy-psdm
Author: Ulf Hamster
Author-email: 554c46@gmail.com
License: MIT
Platform: UNKNOWN
Requires-Python: >=3.6
